issue2branch/issue.py
issue2branch/color.py
issue2branch/format.py
issue2branch/objects.py
issue2branch/repo.py
issue2branch/__init__.py
issue2branch/config.py
issue2branch/trackers/bitbucket.py
issue2branch/trackers/redmine.py
issue2branch/trackers/base.py
issue2branch/trackers/__init__.py
issue2branch/trackers/github.py
issue2branch/utils/requests.py
issue2branch/utils/__init__.py
test/test_config.py
test/test_repo.py
test/test_color.py
test/__init__.py
test/mock_objects.py
test/test_issue.py
test/test_trackers/test_redmine.py
test/test_trackers/test_base.py
test/test_trackers/__init__.py
test/test_trackers/test_github.py
test/test_trackers/test_bitbucket.py
test/test_utils/__init__.py
test/test_utils/test_requests.py
test/utils/mock.py
test/utils/__init__.py
issue2branch-0.0.8.dist-info/DESCRIPTION.rst
issue2branch-0.0.8.dist-info/METADATA
issue2branch-0.0.8.dist-info/WHEEL
issue2branch-0.0.8.dist-info/metadata.json
issue2branch-0.0.8.dist-info/entry_points.txt
issue2branch-0.0.8.dist-info/RECORD
issue2branch-0.0.8.dist-info/top_level.txt
