Metadata-Version: 2.0
Name: issue2branch
Version: 0.0.8
Summary: A feature branch namer / Issue tracker manager
Home-page: https://github.com/pignacio/issue2branch
Author: Ignacio Rossi
Author-email: rossi.ignacio@gmail.com
License: GPLv3
Keywords: issue branch name tracker
Platform: UNKNOWN
Classifier: Development Status :: 4 - Beta
Classifier: License :: OSI Approved :: GNU General Public License v3 (GPLv3)
Classifier: Intended Audience :: Developers
Classifier: Programming Language :: Python :: 2
Classifier: Programming Language :: Python :: 2.7
Classifier: Programming Language :: Python :: 3
Classifier: Programming Language :: Python :: 3.3
Classifier: Programming Language :: Python :: 3.4
Requires-Dist: beautifulsoup4
Requires-Dist: requests (>=2.6.0)
Requires-Dist: six
Requires-Dist: GitPython (>=0.3.6)
